mithrandir/__init__.py
mithrandir/box.py
mithrandir/monad.py
mithrandir/op.py
mithrandir/operators.py
mithrandir-1.4.1.dist-info/entry_points.txt
mithrandir-1.4.1.dist-info/WHEEL
mithrandir-1.4.1.dist-info/METADATA
mithrandir-1.4.1.dist-info/RECORD
