Metadata-Version: 2.1
Name: mithrandir
Version: 1.4.1
Summary: 
Author: vutr
Author-email: me@vutr.io
Requires-Python: >=3.7,<4.0
Classifier: Programming Language :: Python :: 3
Classifier: Programming Language :: Python :: 3.7
Classifier: Programming Language :: Python :: 3.8
